code_sync_mcp/cli.py
code_sync_mcp/client_manager.py
code_sync_mcp/push_handler.py
code_sync_mcp/server.py
code_sync_mcp/websocket_client.py
code_sync_mcp/pb/__init__.py
code_sync_mcp/pb/ws_pb2.py
code_sync_mcp-0.1.6.dist-info/METADATA
code_sync_mcp-0.1.6.dist-info/WHEEL
code_sync_mcp-0.1.6.dist-info/entry_points.txt
code_sync_mcp-0.1.6.dist-info/RECORD
